[
    {
        "title": "Laser Danger",
        "link": "https://xkcd.com/3108/",
        "published": "Fri, 27 Jun 2025 04:00:00 -0000",
        "summary": "<img alt=\"To combat the threat, many airlines are installing wing-mounted spray bottles.\" src=\"https://imgs.xkcd.com/comics/laser_danger.png\" title=\"To combat the threat, many airlines are installing wing-mounted spray bottles.\" />"
    },
    {
        "title": "Weather Balloons",
        "link": "https://xkcd.com/3107/",
        "published": "Wed, 25 Jun 2025 04:00:00 -0000",
        "summary": "<img alt=\"Once you add the balloons into the model, it makes forecasting easier overall--the forecast is always 'cold and dark, with minimal solar-driven convection.'\" src=\"https://imgs.xkcd.com/comics/weather_balloons.png\" title=\"Once you add the balloons into the model, it makes forecasting easier overall--the forecast is always 'cold and dark, with minimal solar-driven convection.'\" />"
    }
]